avstudio/__init__.py
avstudio/avstudio.py
avstudio/avstudio2.py
avstudio/avstudio_devices.py
avstudio/exceptions.py
avstudio-2.0.dist-info/LICENSE.txt
avstudio-2.0.dist-info/METADATA
avstudio-2.0.dist-info/WHEEL
avstudio-2.0.dist-info/top_level.txt
avstudio-2.0.dist-info/RECORD
