Metadata-Version: 2.1
Name: avstudio
Version: 2.0
Summary: Python wrappers for AV Studio public API
Home-page: https://github.com/epiphan-video/avstudio_api
Author: Vadim Kalinskiy
Author-email: vkalinsky@epiphan.com
License: MIT
Project-URL: Documentation, https://epiphan-video.github.io/avstudio_api
Keywords: avstudio
Platform: UNKNOWN
Requires-Python: >=2.7
Requires-Dist: requests
Requires-Dist: requests-toolbelt
